mystpy/__init__.py
mystpy-0.0.1.dist-info/LICENSE
mystpy-0.0.1.dist-info/METADATA
mystpy-0.0.1.dist-info/WHEEL
mystpy-0.0.1.dist-info/top_level.txt
mystpy-0.0.1.dist-info/RECORD
